natsapi/__init__.py
natsapi/_compat.py
natsapi/applications.py
natsapi/asyncapi/__init__.py
natsapi/asyncapi/constants.py
natsapi/asyncapi/models.py
natsapi/asyncapi/utils.py
natsapi/client/__init__.py
natsapi/client/client.py
natsapi/client/config.py
natsapi/context.py
natsapi/encoders.py
natsapi/enums.py
natsapi/exception_handlers.py
natsapi/exceptions.py
natsapi/logger.py
natsapi/models.py
natsapi/plugin.py
natsapi/routing.py
natsapi/state.py
natsapi/types.py
natsapi/utils.py
natsapi-0.1.1.dist-info/LICENSE
natsapi-0.1.1.dist-info/METADATA
natsapi-0.1.1.dist-info/WHEEL
natsapi-0.1.1.dist-info/entry_points.txt
natsapi-0.1.1.dist-info/RECORD
