Metadata-Version: 2.1
Name: natsapi
Version: 0.1.1
Summary: A Python microservice framework that speaks nats.io with asyncapi spec generation capability
Home-page: https://github.com/wegroupwolves/natsapi
License: MIT
Author: WeGroup NV
Author-email: it@wegroup.be
Requires-Python: >=3.9,<4.0
Classifier: License :: OSI Approved :: MIT License
Classifier: Programming Language :: Python :: 3
Classifier: Programming Language :: Python :: 3.9
Classifier: Programming Language :: Python :: 3.10
Classifier: Programming Language :: Python :: 3.11
Classifier: Programming Language :: Python :: 3.12
Classifier: Programming Language :: Python :: 3.13
Requires-Dist: nats-py[nkeys] (>=2.2.0,<3.0.0)
Requires-Dist: pydantic (>=1.7.4,!=1.8,!=1.8.1,!=2.0.0,!=2.0.1,!=2.1.0,<3.0.0)
Requires-Dist: pydantic-settings (>=2.8.1,<3.0.0)
Project-URL: Pypi, https://pypi.org/project/natsapi/
Project-URL: Repository, https://github.com/wegroupwolves/natsapi
